{
    "type": "minecraft:crafting_shaped",
    "pattern": [
        "IWI",
        "RBR",
        "IWI"
    ],
    "key": {
        "I": {
            "item": "minecraft:iron_ingot"
        },
        "R": {
            "item": "minecraft:redstone"
        },
        "B": {
            "item": "minecraft:redstone_block"
        },
        "W": {
            "item": "minecraft:echo_shard"
        }
    },
    "result": {
        "item": "randomredstone:random_redstone_block",
        "count": 1
    }
}